__version__.py
app.py
cli.py
configuration.py
handlers.py
log.py
tasks.py
timetoolkit.py
letsdo-2.0.2.dist-info/licenses/LICENSE
letsdo_scripts/__init__.py
letsdo_scripts/letsdo_completion
tests/__init__.py
tests/test_base.py
tests/test_configuration.py
tests/test_timetoolkit.py
letsdo-2.0.2.dist-info/METADATA
letsdo-2.0.2.dist-info/WHEEL
letsdo-2.0.2.dist-info/entry_points.txt
letsdo-2.0.2.dist-info/top_level.txt
letsdo-2.0.2.dist-info/RECORD
