Metadata-Version: 2.4
Name: letsdo
Version: 2.0.2
Summary: Time tracker for Command Line
Author-email: Carlo Lobrano <c.lobrano@gmail.com>
Project-URL: Homepage, https://github.com/clobrano/letsdo
Project-URL: Issues, https://github.com/clobrano/letsdo/issues
Classifier: Development Status :: 5 - Production/Stable
Classifier: Topic :: Utilities
Classifier: Operating System :: OS Independent
Classifier: License :: OSI Approved :: GNU General Public License v3 (GPLv3)
Requires-Python: >=3.8
License-File: LICENSE
Requires-Dist: docopt
Requires-Dist: PyYaml
Requires-Dist: terminaltables
Requires-Dist: parsedatetime
Requires-Dist: raffaello
Dynamic: license-file
